{
  "schema_version": 1,
  "generated_at": "2025-11-23T01:56:29Z",
  "tools": [
    {
      "id": "day085",
      "slug": "camoforge",
      "title": "CamoForge",
      "subtitle_ja": "迷彩パターン生成ツール",
      "subtitle_en": "A camouflage pattern generator",
      "description_ja": "漆黒・ケーブル群・ハードウェア・オフィス背景など、多様な環境下での迷彩パターンを生成・比較できるWebツール。自然界と人工物の“馴染み方”を体感し、カモフラージュの原理を学ぶ。",
      "description_en": "A web-based camouflage pattern generator that visualizes how colors and textures blend across environments—black matte, cables, hardware panels, and office backgrounds—to study the principles of camouflage and visual integration.",
      "category_ja": [
        "サイバー忍術"
      ],
      "category_en": [
        "Cyber Ninjutsu"
      ],
      "category_ids": [
        "cyber-ninjutsu"
      ],
      "difficulty": 2,
      "tags": [
        "camouflage",
        "visualization",
        "javascript",
        "perlin-noise",
        "research"
      ],
      "repo_url": "https://github.com/ipusiron/camoforge",
      "demo_url": "https://ipusiron.github.io/camoforge/",
      "hub": true
    },
    {
      "id": "day101",
      "slug": "color-hack-box",
      "title": "Color Hack Box",
      "subtitle_ja": "色の三要素を体感する学習ツール",
      "subtitle_en": "Interactive tool to learn hue, saturation & lightness",
      "description_ja": "HSL操作を通じて色相・明度・彩度を直感的に理解できるウェブツール。リアルタイムに視覚フィードバックとカラーコード変換を提供します。",
      "description_en": "An interactive web tool that lets you explore hue, saturation and lightness (HSL) through real-time visual feedback and color code conversion.",
      "category_ja": [
        "Webデザイン",
        "色彩理論"
      ],
      "category_en": [
        "Web Design",
        "Color Theory"
      ],
      "category_ids": [
        "color-theory",
        "web-design"
      ],
      "difficulty": 1,
      "tags": [
        "color",
        "hsl",
        "rgb",
        "hex",
        "color-theory",
        "web",
        "javascript",
        "educational"
      ],
      "repo_url": "https://github.com/ipusiron/color-hack-box",
      "demo_url": "https://ipusiron.github.io/color-hack-box/",
      "hub": true
    },
    {
      "id": "day102",
      "slug": "qrcrashtest",
      "title": "QRCrashTest",
      "subtitle_ja": "QRコード耐性テストツール",
      "subtitle_en": "QR code crash-test visualization tool",
      "description_ja": "影・汚れ・欠損などのダメージに対するQRコードの読み取り耐性を体験できる実験ツール。構造レイヤーと致命ゾーンの可視化により、誤り訂正と当たりどころの違いを直感的に学べる。",
      "description_en": "Interactive crash-test lab for QR codes — simulate shadows, occlusion, dirt, and damage to visualize how QR structure and error correction affect scan survivability.",
      "category_ja": [
        "QRコード",
        "耐タンパー",
        "符号理論"
      ],
      "category_en": [
        "QR code",
        "Anti-Tamper",
        "Coding theory"
      ],
      "category_ids": [
        "coding-theory",
        "qr-code"
      ],
      "difficulty": 3,
      "tags": [
        "qr",
        "qr-code",
        "visualization",
        "image",
        "error-correction",
        "education",
        "javascript"
      ],
      "repo_url": "https://github.com/ipusiron/qrcrashtest",
      "demo_url": "https://ipusiron.github.io/qrcrashtest/",
      "hub": true
    }
  ]
}